README.rst
setup.py
django_pgrunner.egg-info/PKG-INFO
django_pgrunner.egg-info/SOURCES.txt
django_pgrunner.egg-info/dependency_links.txt
django_pgrunner.egg-info/entry_points.txt
django_pgrunner.egg-info/not-zip-safe
django_pgrunner.egg-info/requires.txt
django_pgrunner.egg-info/top_level.txt
pgrunner/__init__.py
pgrunner/commands.py
pgrunner/models.py
pgrunner/management/__init__.py
pgrunner/management/commands/__init__.py
pgrunner/management/commands/pg_activate.py
pgrunner/management/commands/pg_ctl.py
pgrunner/management/commands/pg_dump.py
pgrunner/management/commands/pg_init.py
pgrunner/management/commands/pg_is_running.py
pgrunner/management/commands/pg_psql.py
pgrunner/management/commands/pg_restore.py
pgrunner/management/commands/pg_run.py
pgrunner/management/commands/pg_snapshot.py
pgrunner/management/commands/psql.py