Metadata-Version: 1.0
Name: django-pgrunner
Version: 0.2.2
Summary: Create and autorun a PostgreSQL development database for your Django project
Home-page: https://github.com/wojas/django-pgrunner/
Author: Konrad Wojas
Author-email: konrad@wojas.nl
License: LICENSE
Keywords: django postgres postgresql runner pgrunner
Platform: UNKNOWN
Classifier: Framework :: Django
Classifier: Intended Audience :: Developers
Classifier: Topic :: Database
Classifier: License :: OSI Approved :: MIT License
Classifier: Operating System :: POSIX
Classifier: Operating System :: Unix
Classifier: Operating System :: MacOS :: MacOS X
Classifier: Programming Language :: Python :: 2
Classifier: Programming Language :: Python :: 3
